geneEcomparison/App.py
geneEcomparison/Comparison.py
geneEcomparison/Constants.py
geneEcomparison/HumanMicroarrayData.py
geneEcomparison/HumanRnaSeq.py
geneEcomparison/MouseISHData.py
geneEcomparison/StructureMap.py
geneEcomparison/Utils.py
geneEcomparison/Visualisation.py
geneEcomparison/__init__.py
geneEcomparison/__main__.py
geneEcomparison/annotations/region-assignments.csv
geneEcomparison/annotations/25-micron-ccf/annotation_25.nrrd
geneEcomparison/annotations/P56_Mouse_gridAnnotation/gridAnnotation.mhd
geneEcomparison/annotations/P56_Mouse_gridAnnotation/gridAnnotation.raw
geneEcomparison/assets/styles.css
geneEcomparison-0.0.96.dist-info/LICENSE
geneEcomparison-0.0.96.dist-info/METADATA
geneEcomparison-0.0.96.dist-info/WHEEL
geneEcomparison-0.0.96.dist-info/top_level.txt
geneEcomparison-0.0.96.dist-info/RECORD
