Metadata-Version: 2.1
Name: geneEcomparison
Version: 0.0.96
Summary: Z-score comparison of gene-expression by species
Home-page: https://github.com/christoph-hue/aba-analysis
Author: Christoph Hüsson
Author-email: christoph.huesson@gmx.net
License: UNKNOWN
Project-URL: Bug Tracker, https://github.com/christoph-hue/aba-analysis/issues
Platform: UNKNOWN
Classifier: Programming Language :: Python :: 3
Classifier: License :: OSI Approved :: MIT License
Classifier: Operating System :: OS Independent
Requires-Python: <=3.6.8,>=3.6.7
License-File: LICENSE
Requires-Dist: numpy
Requires-Dist: allensdk
Requires-Dist: dash
Requires-Dist: dash-bootstrap-components
Requires-Dist: dash-extensions
Requires-Dist: openpyxl
